{
  "p1Name": "hey lois",
  "p1Team": "",
  "p1Pron": "i forgot to ask",
  "p1NScore": "0",
  "p1Character": "Snake",
  "p1Skin": "Snake (1)",
  "p1Color": "Red",
  "p1WL": "Nada",
  "p2Name": "jonah",
  "p2Team": "",
  "p2Pron": "he/him",
  "p2NScore": "0",
  "p2Character": "Captain Falcon",
  "p2Skin": "Captain Falcon (1)",
  "p2Color": "Blue",
  "p2WL": "Nada",
  "bestOf": "Bo3",
  "round": "Winners' Round ?",
  "format": "3",
  "tournamentName": "SUS",
  "caster1Name": "it's all about the game.",
  "caster1Twitter": "we gaming",
  "caster1Twitch": "le gaming",
  "caster2Name": "Suffolk Ultimate Scramble 1",
  "caster2Twitter": "waow",
  "caster2Twitch": "stream back on yungcloutgod after today",
  "allowIntro": false
}