{
  "p1Name": "Queen",
  "p1Team": "",
  "p1Pron": "he/him",
  "p1NScore": "0",
  "p1Character": "Peach",
  "p1Skin": "Peach (1)",
  "p1Color": "Red",
  "p1WL": "Nada",
  "p2Name": "Wiloo",
  "p2Team": "Wilsports",
  "p2Pron": "he/him",
  "p2NScore": "1",
  "p2Character": "Cloud",
  "p2Skin": "Cloud (1)",
  "p2Color": "Blue",
  "p2WL": "Nada",
  "bestOf": "Bo3",
  "round": "One of the Rounds",
  "format": "",
  "tournamentName": "SUS 2",
  "caster1Name": "SUS 2",
  "caster1Twitter": "gaming",
  "caster1Twitch": "shoutout cal",
  "caster2Name": "Fall '24",
  "caster2Twitter": "le gaming",
  "caster2Twitch": "shoutout aidan \"gran turismo\" fluffiluff",
  "allowIntro": false
}